botCasSP/CasSP.py
botCasSP/__init__.py
botCasSP/casv2xml.py
botCasSP/casv3xml.py
botCasSP/example/__init__.py
botCasSP/example/cas_client.py
botCasSP/views/__init__.py
botCasSP/views/v3_cas_saml_request.xml
botCasClient-21.9.22.dist-info/METADATA
botCasClient-21.9.22.dist-info/WHEEL
botCasClient-21.9.22.dist-info/top_level.txt
botCasClient-21.9.22.dist-info/RECORD
