Metadata-Version: 2.1
Name: botCasClient
Version: 21.9.22
Summary: CAS Client (SP) for Bottle
Home-page: https://github.com/Glocktober/botCasClient
Author: gunville
Author-email: rk13088@yahoo.com
License: UNKNOWN
Project-URL: repo, https://github.com/Glocktober/botCasClient
Project-URL: overview, https://github.com/Glocktober/botCasClient/blob/main/README.md
Keywords: 'bottle CAS plugin'
Platform: UNKNOWN
Classifier: Programming Language :: Python :: 3
Classifier: License :: OSI Approved :: MIT License
Classifier: Operating System :: OS Independent
Classifier: Framework :: Bottle
Requires-Python: >=3.6
Requires-Dist: bottle (>=0.12.0)
Requires-Dist: BottleSessions (>=21.09.01)
Requires-Dist: defusedxml (>=0.7.1)
Requires-Dist: requests (>=2.20.0)
Requires-Dist: jinja2 (>=3.0.0)
